iwslcxspecapp/SAFEsortingfunctions.py
iwslcxspecapp/__init__.py
iwslcxspecapp/config.yml
iwslcxspecapp/explodesafename.py
iwslcxspecapp/get_path_from_base_SAFE.py
iwslcxspecapp/iw_slc_xspec_visu_panel_app.py
iwslcxspecapp/match_GRD_SLC.py
iwslcxspecapp/shared_information.py
iwslcxspecapp/symmetrize_xspec.py
iwslcxspecapp-0.2.dist-info/LICENSE
iwslcxspecapp-0.2.dist-info/METADATA
iwslcxspecapp-0.2.dist-info/WHEEL
iwslcxspecapp-0.2.dist-info/top_level.txt
iwslcxspecapp-0.2.dist-info/RECORD
